README.md
setup.cfg
setup.py
nomad_pilot_cli/__init__.py
nomad_pilot_cli/api_client.py
nomad_pilot_cli/append_alibaba_headers.py
nomad_pilot_cli/configuration.py
nomad_pilot_cli/exceptions.py
nomad_pilot_cli/rest.py
nomad_pilot_cli/rest_bak.py
nomad_pilot_cli/swagger_validator.py
nomad_pilot_cli.egg-info/PKG-INFO
nomad_pilot_cli.egg-info/SOURCES.txt
nomad_pilot_cli.egg-info/dependency_links.txt
nomad_pilot_cli.egg-info/requires.txt
nomad_pilot_cli.egg-info/top_level.txt
nomad_pilot_cli/api/__init__.py
nomad_pilot_cli/api/batch_api.py
nomad_pilot_cli/api/callback_api.py
nomad_pilot_cli/api/carriers_api.py
nomad_pilot_cli/api/freight_forward_api.py
nomad_pilot_cli/api/inventory_api.py
nomad_pilot_cli/api/inventory_purchase_api.py
nomad_pilot_cli/api/quick_ship_api.py
nomad_pilot_cli/api/ship_api.py
nomad_pilot_cli/api/ship_confirm_api.py
nomad_pilot_cli/models/__init__.py
nomad_pilot_cli/models/address.py
nomad_pilot_cli/models/address_required.py
nomad_pilot_cli/models/address_ship.py
nomad_pilot_cli/models/api_response.py
nomad_pilot_cli/models/api_response_callback.py
nomad_pilot_cli/models/api_response_connector_response.py
nomad_pilot_cli/models/api_response_data.py
nomad_pilot_cli/models/api_response_general.py
nomad_pilot_cli/models/api_response_inventory.py
nomad_pilot_cli/models/callback_body.py
nomad_pilot_cli/models/delivery_status.py
nomad_pilot_cli/models/dimension.py
nomad_pilot_cli/models/goldjet.py
nomad_pilot_cli/models/haiku_delivery_order.py
nomad_pilot_cli/models/inline_object.py
nomad_pilot_cli/models/inline_object1.py
nomad_pilot_cli/models/inventory_base.py
nomad_pilot_cli/models/inventory_product.py
nomad_pilot_cli/models/inventory_purchase.py
nomad_pilot_cli/models/inventory_purchase_item.py
nomad_pilot_cli/models/inventory_response_product.py
nomad_pilot_cli/models/inventory_response_purchase.py
nomad_pilot_cli/models/pack.py
nomad_pilot_cli/models/pack_based.py
nomad_pilot_cli/models/package.py
nomad_pilot_cli/models/package_freight.py
nomad_pilot_cli/models/package_item.py
nomad_pilot_cli/models/package_item_quick.py
nomad_pilot_cli/models/package_items.py
nomad_pilot_cli/models/package_items_quick.py
