Metadata-Version: 2.1
Name: nomad-pilot-cli
Version: 1.53.0
Summary: Nomad Pilot
Home-page: UNKNOWN
Author: OpenAPI Generator community
Author-email: paul@samarkand.global
License: UNKNOWN
Keywords: OpenAPI,OpenAPI-Generator,Nomad Pilot
Platform: UNKNOWN
